psikit/__init__.py
psikit/fsapt_helper.py
psikit/helper_SAPT.py
psikit/psikit.py
psikit/pymol_helper.py
psikit/sapt.py
psikit/util.py
Psikit-0.2.0.dist-info/LICENSE
Psikit-0.2.0.dist-info/METADATA
Psikit-0.2.0.dist-info/WHEEL
Psikit-0.2.0.dist-info/top_level.txt
Psikit-0.2.0.dist-info/RECORD
