Metadata-Version: 2.1
Name: Psikit
Version: 0.2.0
Summary: A thin wrapper library for Psi4 and RDKit
Home-page: https://github.com/Mishima-syk/psikit
Author: Kazufumi Ohkawa, Takayuki Serizawa
Author-email: kerolinq@gmail.com, seritaka@gmail.com
License: MIT
Platform: UNKNOWN
Classifier: Programming Language :: Python
Classifier: Programming Language :: Python :: 3
Requires-Dist: debtcollector
